[{"mainCategory":"a-paraitre","subcategories":["Roman Polar/Suspense","Roman canadien et étranger","Roman québécois","Cuisine santé/diététique","3-6 ans","Internet/Réseaux sociaux","Romans 14 ans et +","Roman graphique","Romans 10-14 ans","Fantastique/SF/Horreur","Rapide/Facile/Économique","Aventure","Nouvelles/Lettres","Poésie","Grossesse/Accouchement","Croissance personnelle"]},{"mainCategory":"affaires-et-communications","subcategories":["Économie/Bourse/Finance","Finances personnelles","Administration/Gestion","Entreprise/Industrie","Gestion ress. hum./Formation","Emploi/Carrière/Études","Communications","Marketing/Vente","Comptabilité","Histoire","Coaching","Dictionnaires","Philosophie/ Métaphysique","Mac/Apple","Culture générale/Quiz","Sciences sociales","Médecines alternatives"]},{"mainCategory":"arts","subcategories":["Architecture/Urbanisme","Beaux livres","Musique/Histoire/Artistes","Médias/Radio/TV/Cinéma","Divers","Arts graphiques/Design/Mode","Photographie","Sciences sociales","Peintres","Histoire","Danse","Culture générale/Quiz","Sculpture","Hist.de l'art / Mouvements","Technique de musique","Street Art","Albums","Tatouage","Céramique/Poterie/Verre","Emploi/Carrière/Études","Sports individuels","Guides Europe","Art","Ésotérisme/Occultisme","Gens d'affaire","Encycl./Atlas/Dictionnaire","Mobilier"]},{"mainCategory":"bande-dessinee","subcategories":["Québécoise","Jeunesse","Historique","Humour","Roman graphique","Botanique/Flore","Manga Shônen","Aventure","Sc-Fiction/Fantastique","Manga Seinen (Adultes)","LGBTQ+","Références","Classiques","Érotique","Polar","Américaine","Western","Manga Shojo","Divers","Illustration"]},{"mainCategory":"biographies","subcategories":["Musique/Chanson","Faits vécus/Bio divers","Sport","Littérature","Cinéma","Sciences","Sciences sociales","Gens d'affaire","Biographies/Témoignages","Soins/Accompagnement","Monarchie/Politique","Art","Cuisine du monde","Histoire","Religion","Essais & critiques littéraires","Éducation/Pédagogie","Médicaments/Maladie","Divers","Musique/Histoire/Artistes","Rapide/Facile/Économique","Médias/Radio/TV/Cinéma"]},{"mainCategory":"cuisine","subcategories":["Divers","Fruits/Légumes","Cuisine du monde","Cuisine santé/diététique","Pain/Pâtes/Pizza","Rapide/Facile/Économique","Confitures/Conserves","Cuisine du Québec","Cuisine végé / végane","Économie/Bourse/Finance","Cuisine","Confiserie/Pâtisserie/Gâteaux","Plat mijoté/Vapeur/Papillote","Buffets/Brunchs/Fêtes","Desserts","Vin/Alcool/Coktails/Bière","Chefs vedette","Fromages","Viandes","Soupes/Potages","Breuvages non-alcoolisés","Poissons/Fruits de mer","Sauces/Vinaigrettes/Huiles","Salades","Encycl./Dictionnaires","Chocolat","Café/Thé/Breuvages chauds","BBQ/Plancha/Cuisine d'été","Entrées/Bouchées","Quiches/Tartes/Crêpes","Cuisine bio","Art de la table","Cuisine au wok","Glaces/Sorbets/Yaourts","Administration/Gestion","Emploi/Carrière/Études"]},{"mainCategory":"esoterisme","subcategories":["Ésotérisme/Occultisme","Croissance personnelle","Méditation/Spiritualité","Parapsychologie/Mort","Médecines alternatives"]},{"mainCategory":"essais","subcategories":["Actualité/Politique","Histoire","Femmes","Québécoise","Sciences sociales","Sexologie","Éducation/Pédagogie","Philosophie/ Métaphysique","Affaires criminelles","Droit/Lois","Théâtre","LGBTQ+","Faits vécus/Bio divers","Biographies/Témoignages","Soins/Accompagnement","Croissance personnelle","Journalisme","Religions","Anthropologie/Archéologie","Encycl./Atlas/Dictionnaire","Géographie"]},{"mainCategory":"faune-flore","subcategories":["Botanique/Flore","Respect des animaux","Divers","Oiseaux","Animaux de la ferme","Animaux de compagnie","Vie aquatique","Insectes/Reptiles/Batraciens","Mammifères","Sciences sociales","Sciences du vivant","Plantes d'intérieur","Philosophie/ Métaphysique","Aquariophilie","Encycl./Atlas/Dictionnaire","Jardinage/Aménagement","Vulgarisation scientifique"]},{"mainCategory":"informatique","subcategories":["Programmation","Internet/Réseaux sociaux","Jeux/Livres-jeu/Blagues","Albums","Documentaires","Bureautique-Office","Système d'exploitation","Utilitaires","Réseaux/Serveurs","Initiation","Site Web / Blog","Tél.int./Tablette/iPad/iWatch","Base de données","Cahiers Jeux/Apprentissage","Sciences sociales","Encycl./Atlas/Dictionnaire","Communications","Multimédia/Audionumérique","Mac/Apple","Contes/Poésie/Théâtre","Cuisine","Graphisme","Essais & critiques littéraires","Référence","Langues"]},{"mainCategory":"jeunesse","subcategories":["Romans 14 ans et +","Romans 10-14 ans","3-6 ans","Documentaires","Romans 6-10 ans","Albums","0-3 ans","Émotions/Comportements","Contes/Poésie/Théâtre","Activités créatives","Jeux/Livres-jeu/Blagues","Cuisine","Noël/Halloween/Pâques","Agendas/Calendriers/ Carnets"]},{"mainCategory":"langues","subcategories":["Grammaire/Conj./Orthographe","Dictionnaire français","Écriture et style","Apprentissage des langues","Linguistique","Traduction","Lecture en français facile","Sciences sociales","Dictionnaire autres langues","Dictionnaire anglais","Livre bilingue","Philosophie/ Métaphysique","Guides de conversation"]},{"mainCategory":"litterature","subcategories":["Roman québécois","Roman canadien et étranger","Roman Polar/Suspense","Poésie","Contes/Légendes","Nouvelles/Lettres","Essais & critiques littéraires","Fantastique/SF/Horreur","Romans et nouvelles érotiques","Théâtre","Récits","Sciences sociales","Littérature","Polar","Contes/Poésie/Théâtre","Dictionnaire/Anthologie","Écriture et style"]},{"mainCategory":"loisirs","subcategories":["Jeux variés/Passe-temps","Jardinage/Aménagement","Humour","Dictionnaire français","Agendas/Calendriers/Carnets","Jeux de lettres","Jeux vidéo/électroniques","Agriculture/Agriproduction","Loisirs créatifs","Plantes d'intérieur","Sciences sociales","Bricolage/Menuiserie","Coloriage anti-stress Adultes","Médias/Radio/TV/Cinéma","Sudoku/Logique/Énigmes","Techniques peinture/dessin","Éducation/Pédagogie","Fantastique/SF/Horreur","Culture générale/Quiz","Divers","Guides Europe","Décoration","Jeux/Livres-jeu/Blagues","Théâtre","Calligraphie","Jeux de cartes/de table","Techniques photo/vidéo","Collections","Dictionnaire/Anthologie","Encycl./Atlas/Dictionnaire","Guides Les Amériques","Littérature","Peintres","Albums","Guides de conversation","Botanique/Flore","Emploi/Carrière/Études"]},{"mainCategory":"nouveautes","subcategories":["Actualité/Politique","Romans 14 ans et +","Architecture/Urbanisme","Roman Polar/Suspense","Poésie","Musique/Chanson","Roman québécois","Québécoise","Historique","Roman canadien et étranger","Nouvelles/Lettres","Roman graphique","Femmes","Sciences sociales","3-6 ans","Romans 6-10 ans","Jeux variés/Passe-temps","Albums","Jeunesse","Essais & critiques littéraires","Émotions/Comportements","Manga Shônen","Affaires criminelles","Documentaires","Romans 10-14 ans","Botanique/Flore","Musique/Histoire/Artistes","Sciences du vivant","Rapide/Facile/Économique","Récits aventuriers / voyageurs","Fantastique/SF/Horreur","Grossesse/Accouchement","Droit/Lois","Intelligence artificielle","Chimie/Physique/Astrophysique","Cuisine du monde","Psychologie/Psychiatrie","Croissance personnelle","Contes/Poésie/Théâtre","Arts graphiques/Design/Mode","Médias/Radio/TV/Cinéma","Écologie/Environnement","Changement climatique","Revues culturelles","Histoire","Médecines alternatives","Divers","Entreprise/Industrie","Théâtre","Philosophie/ Métaphysique","Faits vécus/Bio divers","0-3 ans","Desserts","Aventure","Manga Seinen (Adultes)","Buffets/Brunchs/Fêtes","Plat mijoté/Vapeur/Papillote","Cuisine végé / végane"]},{"mainCategory":"palmares","subcategories":["Jeunesse","Humour","Roman québécois","Actualité/Politique","Poésie","Musique/Chanson","Roman canadien et étranger","Architecture/Urbanisme","Romans 10-14 ans","Roman Polar/Suspense","Sport","Contes/Légendes","Religions","Manga Shônen","Québécoise","Histoire","Essais & critiques littéraires","Croissance personnelle","Sports d'équipe","Faits vécus/Bio divers","Romans 14 ans et +","Romans 6-10 ans","0-3 ans","Récits aventuriers / voyageurs"]},{"mainCategory":"psychologie","subcategories":["Croissance personnelle","Psychologie/Psychiatrie","Rêves","Bien-être et spiritualité","Pensées/Proverbes","Administration/Gestion","Guide pratique","Méditation/Spiritualité","Philosophie/ Métaphysique"]},{"mainCategory":"sante","subcategories":["Alimentation","Médecines alternatives","Médicaments/Maladie","En forme/Régimes/Yoga","Histoire de la médecine","Médecine conventionnelle","Dépendances","Guide pratique","Faits vécus/Bio divers","Biographies/Témoignages","Soins/Accompagnement","Parascolaire","Croissance personnelle","Aînés","Sexualité","Encycl./Dictionnaire","Parentalité","Troubles de l'enfance","Beauté/Vêtements/Accessoires","Sciences du vivant","Roman Polar/Suspense","Cuisine santé/diététique"]},{"mainCategory":"science-technologie","subcategories":["Chimie/Physique/Astrophysique","Sciences du vivant","Intelligence artificielle","Documentaires","Écologie/Environnement","Changement climatique","Agriculture/Agriproduction","Eau/Énergie/Ressources","Divers","Astronomie","Mathématiques","Vulgarisation scientifique","Sciences de la Terre","Technologie","Génétique","Botanique/Flore","Géologie/Minéraux/Pierres","Médecine vétérinaire","Ingénierie","Mammifères","Animaux de compagnie","Sciences sociales","Encycl./Atlas/Dictionnaire","Insectes/Reptiles/Batraciens"]},{"mainCategory":"spiritualite-religion","subcategories":["Religions","Vie chrétienne","Croissance personnelle","Symboles/Mythologie/Croyances","Méditation/Spiritualité","Essais & critiques littéraires","Parapsychologie/Mort","Ésotérisme/Occultisme","Faits vécus/Bio divers","Bien-être et spiritualité","Anges","Histoire","Respect des animaux","Divers","Agendas/Calendriers/Carnets","Mandalas"]},{"mainCategory":"sports","subcategories":["Activités de plein air","Croissance personnelle","Sports d'équipe","Sports équestres","Psychologie/Psychiatrie","Sports individuels","Chasse/Pêche","Sports extrêmes","Athlétisme/Olympisme","Divers","Sports aquatiques/nautiques","Cond.phys./Musculation","Sports combat/Arts martiaux","Sport","Balades Randonnées","Animaux de la ferme","En forme/Régimes/Yoga"]},{"mainCategory":"vie-pratique","subcategories":["Sexualité","Grossesse/Accouchement","Parentalité","Relations dans le couple","Guide pratique","Beauté/Vêtements/Accessoires","Troubles de l'enfance","Adolescence","Parascolaire","Album bébés/Prénoms","Alimentation/enfants","Psychologie/Psychiatrie","Paternité","Loisirs créatifs","Familles éclatées/recomposées","Politesse/Savoir-vivre","Guides Asie","Techniques peinture/dessin","Trucs/Astuces","Jeux variés/Passe-temps","Calligraphie","Bricolage/Menuiserie","Jeux vidéo/électroniques","Sciences sociales","Croissance personnelle","Jeux de lettres","Médecines alternatives","Cahiers Jeux/Apprentissage","Jeux/Livres-jeu/Blagues"]},{"mainCategory":"voyages","subcategories":["Récits aventuriers / voyageurs","Ouvrages généraux","Guides Les Amériques","Balades Randonnées","Guides Europe","Contes/Légendes","Guides Océans Pacifique/Indien","Guides Asie","Albums","Hôtels/Restaurants","Sports individuels","Vie chrétienne","Symboles/Mythologie/Croyances","Méditation/Spiritualité","Religions","Guides Afrique","Photographie","Guides de conversation","Apprentissage des langues","Histoire","Beaux livres"]}]